[
  {
    "word": "一",
    "pinyin": "yī",
    "part_of_speech": "numeral",
    "meaning": "one",
    "chapter": 1,
    "source": "hsk1",
    "category": "number"
  },
  {
    "word": "三",
    "pinyin": "sān",
    "part_of_speech": "numeral",
    "meaning": "three",
    "chapter": 1,
    "source": "hsk1",
    "category": "number"
  },
  {
    "word": "二",
    "pinyin": "èr",
    "part_of_speech": "numeral",
    "meaning": "two",
    "chapter": 1,
    "source": "hsk1",
    "category": "number"
  },
  {
    "word": "你",
    "pinyin": "nǐ",
    "part_of_speech": "pronoun",
    "meaning": "(singular) you",
    "chapter": 1,
    "source": "hsk1",
    "category": "pronoun"
  },
  {
    "word": "你们",
    "pinyin": "nǐmen",
    "part_of_speech": "pronoun",
    "meaning": "(plural) you",
    "chapter": 1,
    "source": "hsk1",
    "category": "pronoun"
  },
  {
    "word": "八",
    "pinyin": "bā",
    "part_of_speech": "numeral",
    "meaning": "eight",
    "chapter": 1,
    "source": "hsk1",
    "category": "number"
  },
  {
    "word": "六",
    "pinyin": "liù",
    "part_of_speech": "numeral",
    "meaning": "six",
    "chapter": 1,
    "source": "hsk1",
    "category": "number"
  },
  {
    "word": "十",
    "pinyin": "shí",
    "part_of_speech": "numeral",
    "meaning": "ten",
    "chapter": 1,
    "source": "hsk1",
    "category": "number"
  },
  {
    "word": "天",
    "pinyin": "tiān",
    "part_of_speech": "noun",
    "meaning": "sky, day",
    "chapter": 1,
    "source": "hsk1",
    "category": "nature"
  },
  {
    "word": "好",
    "pinyin": "hǎo",
    "part_of_speech": "adjective",
    "meaning": "good, fine",
    "chapter": 1,
    "source": "hsk1",
    "category": "emotion"
  },
  {
    "word": "对不起",
    "pinyin": "duìbuqǐ",
    "part_of_speech": "verb",
    "meaning": "to be sorry",
    "chapter": 1,
    "source": "hsk1",
    "category": "greeting"
  },
  {
    "word": "您",
    "pinyin": "nín",
    "part_of_speech": "pronoun",
    "meaning": "(polite) you",
    "chapter": 1,
    "source": "hsk1",
    "category": "pronoun"
  },
  {
    "word": "没关系",
    "pinyin": "méi guānxi",
    "part_of_speech": "interjection",
    "meaning": "it's OK, no problem",
    "chapter": 1,
    "source": "hsk1",
    "category": "greeting"
  },
  {
    "word": "马",
    "pinyin": "mǎ",
    "part_of_speech": "noun",
    "meaning": "horse",
    "chapter": 1,
    "source": "hsk1",
    "category": "animal"
  },
  {
    "word": "鱼",
    "pinyin": "yú",
    "part_of_speech": "noun",
    "meaning": "fish",
    "chapter": 1,
    "source": "hsk1",
    "category": "animal"
  },
  {
    "word": "不",
    "pinyin": "bù",
    "part_of_speech": "adverb",
    "meaning": "no, not",
    "chapter": 2,
    "source": "hsk1",
    "category": "grammar"
  },
  {
    "word": "不客气",
    "pinyin": "bù kèqi",
    "part_of_speech": "interjection",
    "meaning": "you're welcome",
    "chapter": 2,
    "source": "hsk1",
    "category": "greeting"
  },
  {
    "word": "云",
    "pinyin": "yún",
    "part_of_speech": "noun",
    "meaning": "cloud",
    "chapter": 2,
    "source": "hsk1",
    "category": "nature"
  },
  {
    "word": "什么",
    "pinyin": "shénme",
    "part_of_speech": "pronoun",
    "meaning": "what",
    "chapter": 2,
    "source": "hsk1",
    "category": "pronoun"
  },
  {
    "word": "再见",
    "pinyin": "zàijiàn",
    "part_of_speech": "verb",
    "meaning": "to see you around",
    "chapter": 2,
    "source": "hsk1",
    "category": "greeting"
  },
  {
    "word": "叫",
    "pinyin": "jiào",
    "part_of_speech": "verb",
    "meaning": "to call, to be called",
    "chapter": 2,
    "source": "hsk1",
    "category": "communication"
  },
  {
    "word": "名字",
    "pinyin": "míngzi",
    "part_of_speech": "noun",
    "meaning": "name",
    "chapter": 2,
    "source": "hsk1",
    "category": "communication"
  },
  {
    "word": "山",
    "pinyin": "shān",
    "part_of_speech": "noun",
    "meaning": "mountain",
    "chapter": 2,
    "source": "hsk1",
    "category": "nature"
  },
  {
    "word": "我",
    "pinyin": "wǒ",
    "part_of_speech": "pronoun",
    "meaning": "I, me",
    "chapter": 2,
    "source": "hsk1",
    "category": "pronoun"
  },
  {
    "word": "手",
    "pinyin": "shǒu",
    "part_of_speech": "noun",
    "meaning": "hand",
    "chapter": 2,
    "source": "hsk1",
    "category": "body"
  },
  {
    "word": "羊",
    "pinyin": "yáng",
    "part_of_speech": "noun",
    "meaning": "sheep, goat",
    "chapter": 2,
    "source": "hsk1",
    "category": "animal"
  },
  {
    "word": "谢谢",
    "pinyin": "xièxie",
    "part_of_speech": "verb",
    "meaning": "to thank",
    "chapter": 2,
    "source": "hsk1",
    "category": "greeting"
  },
  {
    "word": "零",
    "pinyin": "líng",
    "part_of_speech": "numeral",
    "meaning": "zero",
    "chapter": 2,
    "source": "hsk1",
    "category": "number"
  },
  {
    "word": "中",
    "pinyin": "zhōng",
    "part_of_speech": "noun",
    "meaning": "middle, center",
    "chapter": 3,
    "source": "hsk1",
    "category": "direction"
  },
  {
    "word": "中国",
    "pinyin": "Zhōngguó",
    "part_of_speech": "noun",
    "meaning": "China",
    "chapter": 3,
    "source": "hsk1",
    "category": "country"
  },
  {
    "word": "人",
    "pinyin": "rén",
    "part_of_speech": "noun",
    "meaning": "human, person",
    "chapter": 3,
    "source": "hsk1",
    "category": "person"
  },
  {
    "word": "吗",
    "pinyin": "ma",
    "part_of_speech": "particle",
    "meaning": "question particle",
    "chapter": 3,
    "source": "hsk1",
    "category": "grammar"
  },
  {
    "word": "学生",
    "pinyin": "xuéshēng",
    "part_of_speech": "noun",
    "meaning": "student",
    "chapter": 3,
    "source": "hsk1",
    "category": "person"
  },
  {
    "word": "工",
    "pinyin": "gōng",
    "part_of_speech": "noun",
    "meaning": "work, labor",
    "chapter": 3,
    "source": "hsk1",
    "category": "action"
  },
  {
    "word": "心",
    "pinyin": "xīn",
    "part_of_speech": "noun",
    "meaning": "heart",
    "chapter": 3,
    "source": "hsk1",
    "category": "body"
  },
  {
    "word": "是",
    "pinyin": "shì",
    "part_of_speech": "verb",
    "meaning": "to be",
    "chapter": 3,
    "source": "hsk1",
    "category": "grammar"
  },
  {
    "word": "美国",
    "pinyin": "Měiguó",
    "part_of_speech": "noun",
    "meaning": "USA, America",
    "chapter": 3,
    "source": "hsk1",
    "category": "country"
  },
  {
    "word": "老师",
    "pinyin": "lǎoshī",
    "part_of_speech": "noun",
    "meaning": "teacher",
    "chapter": 3,
    "source": "hsk1",
    "category": "person"
  },
  {
    "word": "七",
    "pinyin": "qī",
    "part_of_speech": "numeral",
    "meaning": "seven",
    "chapter": 4,
    "source": "hsk1",
    "category": "number"
  },
  {
    "word": "九",
    "pinyin": "jiǔ",
    "part_of_speech": "numeral",
    "meaning": "nine",
    "chapter": 4,
    "source": "hsk1",
    "category": "number"
  },
  {
    "word": "他",
    "pinyin": "tā",
    "part_of_speech": "pronoun",
    "meaning": "he, him",
    "chapter": 4,
    "source": "hsk1",
    "category": "pronoun"
  },
  {
    "word": "儿",
    "pinyin": "ér",
    "part_of_speech": "noun",
    "meaning": "child; diminutive suffix (e.g., 一点儿, 那儿)",
    "chapter": 4,
    "source": "hsk1",
    "category": "family"
  },
  {
    "word": "同学",
    "pinyin": "tóngxué",
    "part_of_speech": "noun",
    "meaning": "classmate",
    "chapter": 4,
    "source": "hsk1",
    "category": "person"
  },
  {
    "word": "呢",
    "pinyin": "ne",
    "part_of_speech": "particle",
    "meaning": "follow-up particle",
    "chapter": 4,
    "source": "hsk1",
    "category": "grammar"
  },
  {
    "word": "哪",
    "pinyin": "nǎ",
    "part_of_speech": "pronoun",
    "meaning": "which",
    "chapter": 4,
    "source": "hsk1",
    "category": "pronoun"
  },
  {
    "word": "国",
    "pinyin": "guó",
    "part_of_speech": "noun",
    "meaning": "country, nation",
    "chapter": 4,
    "source": "hsk1",
    "category": "country"
  },
  {
    "word": "她",
    "pinyin": "tā",
    "part_of_speech": "pronoun",
    "meaning": "she, her",
    "chapter": 4,
    "source": "hsk1",
    "category": "pronoun"
  },
  {
    "word": "朋友",
    "pinyin": "péngyǒu",
    "part_of_speech": "noun",
    "meaning": "friend",
    "chapter": 4,
    "source": "hsk1",
    "category": "person"
  },
  {
    "word": "汉语",
    "pinyin": "Hànyǔ",
    "part_of_speech": "noun",
    "meaning": "Chinese (language)",
    "chapter": 4,
    "source": "hsk1",
    "category": "communication"
  },
  {
    "word": "的",
    "pinyin": "de",
    "part_of_speech": "particle",
    "meaning": "possession marker",
    "chapter": 4,
    "source": "hsk1",
    "category": "grammar"
  },
  {
    "word": "谁",
    "pinyin": "shéi",
    "part_of_speech": "pronoun",
    "meaning": "who, whom",
    "chapter": 4,
    "source": "hsk1",
    "category": "pronoun"
  },
  {
    "word": "了",
    "pinyin": "le",
    "part_of_speech": "particle",
    "meaning": "change-of-state particle",
    "chapter": 5,
    "source": "hsk1",
    "category": "grammar"
  },
  {
    "word": "五",
    "pinyin": "wǔ",
    "part_of_speech": "numeral",
    "meaning": "five",
    "chapter": 5,
    "source": "hsk1",
    "category": "number"
  },
  {
    "word": "今年",
    "pinyin": "jīnnián",
    "part_of_speech": "noun",
    "meaning": "this year",
    "chapter": 5,
    "source": "hsk1",
    "category": "time"
  },
  {
    "word": "几",
    "pinyin": "jǐ",
    "part_of_speech": "pronoun",
    "meaning": "how many (small number)",
    "chapter": 5,
    "source": "hsk1",
    "category": "pronoun"
  },
  {
    "word": "口",
    "pinyin": "kǒu",
    "part_of_speech": "measure_word",
    "meaning": "mouth; MW (family)",
    "chapter": 5,
    "source": "hsk1",
    "category": "body"
  },
  {
    "word": "四",
    "pinyin": "sì",
    "part_of_speech": "numeral",
    "meaning": "four",
    "chapter": 5,
    "source": "hsk1",
    "category": "number"
  },
  {
    "word": "多",
    "pinyin": "duō",
    "part_of_speech": "adverb",
    "meaning": "many, much; how (degree)",
    "chapter": 5,
    "source": "hsk1",
    "category": "size"
  },
  {
    "word": "大",
    "pinyin": "dà",
    "part_of_speech": "adjective",
    "meaning": "big, large; (of age) old",
    "chapter": 5,
    "source": "hsk1",
    "category": "size"
  },
  {
    "word": "女",
    "pinyin": "nǚ",
    "part_of_speech": "noun",
    "meaning": "woman, female",
    "chapter": 5,
    "source": "hsk1",
    "category": "person"
  },
  {
    "word": "女儿",
    "pinyin": "nǚ'ér",
    "part_of_speech": "noun",
    "meaning": "daughter",
    "chapter": 5,
    "source": "hsk1",
    "category": "family"
  },
  {
    "word": "家",
    "pinyin": "jiā",
    "part_of_speech": "noun",
    "meaning": "home, family",
    "chapter": 5,
    "source": "hsk1",
    "category": "family"
  },
  {
    "word": "岁",
    "pinyin": "suì",
    "part_of_speech": "measure_word",
    "meaning": "year (of age)",
    "chapter": 5,
    "source": "hsk1",
    "category": "time"
  },
  {
    "word": "有",
    "pinyin": "yǒu",
    "part_of_speech": "verb",
    "meaning": "to have, there be",
    "chapter": 5,
    "source": "hsk1",
    "category": "grammar"
  },
  {
    "word": "百",
    "pinyin": "bǎi",
    "part_of_speech": "numeral",
    "meaning": "hundred",
    "chapter": 5,
    "source": "hsk1",
    "category": "number"
  },
  {
    "word": "东",
    "pinyin": "dōng",
    "part_of_speech": "noun",
    "meaning": "east",
    "chapter": 6,
    "source": "hsk1",
    "category": "direction"
  },
  {
    "word": "会",
    "pinyin": "huì",
    "part_of_speech": "verb",
    "meaning": "can (learned skill)",
    "chapter": 6,
    "source": "hsk1",
    "category": "grammar"
  },
  {
    "word": "做",
    "pinyin": "zuò",
    "part_of_speech": "verb",
    "meaning": "to make, to produce",
    "chapter": 6,
    "source": "hsk1",
    "category": "action"
  },
  {
    "word": "写",
    "pinyin": "xiě",
    "part_of_speech": "verb",
    "meaning": "to write",
    "chapter": 6,
    "source": "hsk1",
    "category": "communication"
  },
  {
    "word": "妈妈",
    "pinyin": "māma",
    "part_of_speech": "noun",
    "meaning": "mother",
    "chapter": 6,
    "source": "hsk1",
    "category": "family"
  },
  {
    "word": "字",
    "pinyin": "zì",
    "part_of_speech": "noun",
    "meaning": "character, word",
    "chapter": 6,
    "source": "hsk1",
    "category": "communication"
  },
  {
    "word": "很",
    "pinyin": "hěn",
    "part_of_speech": "adverb",
    "meaning": "very, quite",
    "chapter": 6,
    "source": "hsk1",
    "category": "grammar"
  },
  {
    "word": "怎么",
    "pinyin": "zěnme",
    "part_of_speech": "pronoun",
    "meaning": "how (to do)",
    "chapter": 6,
    "source": "hsk1",
    "category": "pronoun"
  },
  {
    "word": "汉字",
    "pinyin": "Hànzì",
    "part_of_speech": "noun",
    "meaning": "Chinese character",
    "chapter": 6,
    "source": "hsk1",
    "category": "communication"
  },
  {
    "word": "菜",
    "pinyin": "cài",
    "part_of_speech": "noun",
    "meaning": "dish, cuisine",
    "chapter": 6,
    "source": "hsk1",
    "category": "food"
  },
  {
    "word": "好吃",
    "pinyin": "hǎochī",
    "part_of_speech": "adjective",
    "meaning": "delicious, tasty",
    "chapter": 6,
    "source": "hsk1",
    "category": "food"
  },
  {
    "word": "西",
    "pinyin": "xī",
    "part_of_speech": "noun",
    "meaning": "west",
    "chapter": 6,
    "source": "hsk1",
    "category": "direction"
  },
  {
    "word": "说",
    "pinyin": "shuō",
    "part_of_speech": "verb",
    "meaning": "to speak, to say",
    "chapter": 6,
    "source": "hsk1",
    "category": "communication"
  },
  {
    "word": "读",
    "pinyin": "dú",
    "part_of_speech": "verb",
    "meaning": "to read",
    "chapter": 6,
    "source": "hsk1",
    "category": "communication"
  },
  {
    "word": "中国菜",
    "pinyin": "Zhōngguó cài",
    "part_of_speech": "noun",
    "meaning": "Chinese food",
    "chapter": 7,
    "source": "hsk1",
    "category": "food"
  },
  {
    "word": "书",
    "pinyin": "shū",
    "part_of_speech": "noun",
    "meaning": "book",
    "chapter": 7,
    "source": "hsk1",
    "category": "object"
  },
  {
    "word": "今天",
    "pinyin": "jīntiān",
    "part_of_speech": "noun",
    "meaning": "today",
    "chapter": 7,
    "source": "hsk1",
    "category": "time"
  },
  {
    "word": "去",
    "pinyin": "qù",
    "part_of_speech": "verb",
    "meaning": "to go",
    "chapter": 7,
    "source": "hsk1",
    "category": "movement"
  },
  {
    "word": "号",
    "pinyin": "hào",
    "part_of_speech": "noun",
    "meaning": "date number",
    "chapter": 7,
    "source": "hsk1",
    "category": "time"
  },
  {
    "word": "银行",
    "pinyin": "yínháng",
    "part_of_speech": "noun",
    "meaning": "bank",
    "chapter": 7,
    "source": "hsk1",
    "category": "place"
  },
  {
    "word": "日历",
    "pinyin": "rìlì",
    "part_of_speech": "noun",
    "meaning": "calendar",
    "chapter": 7,
    "source": "hsk1",
    "category": "time"
  },
  {
    "word": "学校",
    "pinyin": "xuéxiào",
    "part_of_speech": "noun",
    "meaning": "school",
    "chapter": 7,
    "source": "hsk1",
    "category": "place"
  },
  {
    "word": "明天",
    "pinyin": "míngtiān",
    "part_of_speech": "noun",
    "meaning": "tomorrow",
    "chapter": 7,
    "source": "hsk1",
    "category": "time"
  },
  {
    "word": "星期",
    "pinyin": "xīngqī",
    "part_of_speech": "noun",
    "meaning": "week",
    "chapter": 7,
    "source": "hsk1",
    "category": "time"
  },
  {
    "word": "昨天",
    "pinyin": "zuótiān",
    "part_of_speech": "noun",
    "meaning": "yesterday",
    "chapter": 7,
    "source": "hsk1",
    "category": "time"
  },
  {
    "word": "月",
    "pinyin": "yuè",
    "part_of_speech": "noun",
    "meaning": "month",
    "chapter": 7,
    "source": "hsk1",
    "category": "time"
  },
  {
    "word": "看",
    "pinyin": "kàn",
    "part_of_speech": "verb",
    "meaning": "to look, watch, read",
    "chapter": 7,
    "source": "hsk1",
    "category": "action"
  },
  {
    "word": "请",
    "pinyin": "qǐng",
    "part_of_speech": "verb",
    "meaning": "(polite) please",
    "chapter": 7,
    "source": "hsk1",
    "category": "greeting"
  },
  {
    "word": "问",
    "pinyin": "wèn",
    "part_of_speech": "verb",
    "meaning": "to ask, to inquire",
    "chapter": 7,
    "source": "hsk1",
    "category": "communication"
  },
  {
    "word": "一月",
    "pinyin": "yīyuè",
    "part_of_speech": "noun",
    "meaning": "January",
    "chapter": 7,
    "source": "hsk1",
    "category": "time"
  },
  {
    "word": "二月",
    "pinyin": "èryuè",
    "part_of_speech": "noun",
    "meaning": "February",
    "chapter": 7,
    "source": "hsk1",
    "category": "time"
  },
  {
    "word": "三月",
    "pinyin": "sānyuè",
    "part_of_speech": "noun",
    "meaning": "March",
    "chapter": 7,
    "source": "hsk1",
    "category": "time"
  },
  {
    "word": "四月",
    "pinyin": "sìyuè",
    "part_of_speech": "noun",
    "meaning": "April",
    "chapter": 7,
    "source": "hsk1",
    "category": "time"
  },
  {
    "word": "五月",
    "pinyin": "wǔyuè",
    "part_of_speech": "noun",
    "meaning": "May",
    "chapter": 7,
    "source": "hsk1",
    "category": "time"
  },
  {
    "word": "六月",
    "pinyin": "liùyuè",
    "part_of_speech": "noun",
    "meaning": "June",
    "chapter": 7,
    "source": "hsk1",
    "category": "time"
  },
  {
    "word": "七月",
    "pinyin": "qīyuè",
    "part_of_speech": "noun",
    "meaning": "July",
    "chapter": 7,
    "source": "hsk1",
    "category": "time"
  },
  {
    "word": "八月",
    "pinyin": "bāyuè",
    "part_of_speech": "noun",
    "meaning": "August",
    "chapter": 7,
    "source": "hsk1",
    "category": "time"
  },
  {
    "word": "九月",
    "pinyin": "jiǔyuè",
    "part_of_speech": "noun",
    "meaning": "September",
    "chapter": 7,
    "source": "hsk1",
    "category": "time"
  },
  {
    "word": "十月",
    "pinyin": "shíyuè",
    "part_of_speech": "noun",
    "meaning": "October",
    "chapter": 7,
    "source": "hsk1",
    "category": "time"
  },
  {
    "word": "十一月",
    "pinyin": "shíyīyuè",
    "part_of_speech": "noun",
    "meaning": "November",
    "chapter": 7,
    "source": "hsk1",
    "category": "time"
  },
  {
    "word": "十二月",
    "pinyin": "shí'èryuè",
    "part_of_speech": "noun",
    "meaning": "December",
    "chapter": 7,
    "source": "hsk1",
    "category": "time"
  },
  {
    "word": "星期一",
    "pinyin": "xīngqīyī",
    "part_of_speech": "noun",
    "meaning": "Monday",
    "chapter": 7,
    "source": "hsk1",
    "category": "time"
  },
  {
    "word": "星期二",
    "pinyin": "xīngqī'èr",
    "part_of_speech": "noun",
    "meaning": "Tuesday",
    "chapter": 7,
    "source": "hsk1",
    "category": "time"
  },
  {
    "word": "星期三",
    "pinyin": "xīngqīsān",
    "part_of_speech": "noun",
    "meaning": "Wednesday",
    "chapter": 7,
    "source": "hsk1",
    "category": "time"
  },
  {
    "word": "星期四",
    "pinyin": "xīngqīsì",
    "part_of_speech": "noun",
    "meaning": "Thursday",
    "chapter": 7,
    "source": "hsk1",
    "category": "time"
  },
  {
    "word": "星期五",
    "pinyin": "xīngqīwǔ",
    "part_of_speech": "noun",
    "meaning": "Friday",
    "chapter": 7,
    "source": "hsk1",
    "category": "time"
  },
  {
    "word": "星期六",
    "pinyin": "xīngqīliù",
    "part_of_speech": "noun",
    "meaning": "Saturday",
    "chapter": 7,
    "source": "hsk1",
    "category": "time"
  },
  {
    "word": "星期天",
    "pinyin": "xīngqītiān",
    "part_of_speech": "noun",
    "meaning": "Sunday",
    "chapter": 7,
    "source": "hsk1",
    "category": "time"
  },
  {
    "word": "下午",
    "pinyin": "xiàwǔ",
    "part_of_speech": "noun",
    "meaning": "afternoon",
    "chapter": 8,
    "source": "hsk1",
    "category": "time"
  },
  {
    "word": "个",
    "pinyin": "ge",
    "part_of_speech": "measure_word",
    "meaning": "general measure word",
    "chapter": 8,
    "source": "hsk1",
    "category": "grammar"
  },
  {
    "word": "买",
    "pinyin": "mǎi",
    "part_of_speech": "verb",
    "meaning": "to buy, to purchase",
    "chapter": 8,
    "source": "hsk1",
    "category": "action"
  },
  {
    "word": "吃",
    "pinyin": "chī",
    "part_of_speech": "verb",
    "meaning": "to eat",
    "chapter": 8,
    "source": "hsk1",
    "category": "food"
  },
  {
    "word": "商店",
    "pinyin": "shāngdiàn",
    "part_of_speech": "noun",
    "meaning": "shop, store",
    "chapter": 8,
    "source": "hsk1",
    "category": "place"
  },
  {
    "word": "喝",
    "pinyin": "hē",
    "part_of_speech": "verb",
    "meaning": "to drink",
    "chapter": 8,
    "source": "hsk1",
    "category": "food"
  },
  {
    "word": "块",
    "pinyin": "kuài",
    "part_of_speech": "measure_word",
    "meaning": "yuan (money unit)",
    "chapter": 8,
    "source": "hsk1",
    "category": "number"
  },
  {
    "word": "多少",
    "pinyin": "duōshao",
    "part_of_speech": "pronoun",
    "meaning": "how many, how much",
    "chapter": 8,
    "source": "hsk1",
    "category": "size"
  },
  {
    "word": "想",
    "pinyin": "xiǎng",
    "part_of_speech": "verb",
    "meaning": "to think, would like to",
    "chapter": 8,
    "source": "hsk1",
    "category": "emotion"
  },
  {
    "word": "要",
    "pinyin": "yào",
    "part_of_speech": "verb",
    "meaning": "to want, to need",
    "chapter": 8,
    "source": "hsk1",
    "category": "action"
  },
  {
    "word": "杯子",
    "pinyin": "bēizi",
    "part_of_speech": "noun",
    "meaning": "cup, glass",
    "chapter": 8,
    "source": "hsk1",
    "category": "food"
  },
  {
    "word": "米饭",
    "pinyin": "mǐfàn",
    "part_of_speech": "noun",
    "meaning": "cooked rice",
    "chapter": 8,
    "source": "hsk1",
    "category": "food"
  },
  {
    "word": "茶",
    "pinyin": "chá",
    "part_of_speech": "noun",
    "meaning": "tea",
    "chapter": 8,
    "source": "hsk1",
    "category": "food"
  },
  {
    "word": "这",
    "pinyin": "zhè",
    "part_of_speech": "pronoun",
    "meaning": "this",
    "chapter": 8,
    "source": "hsk1",
    "category": "pronoun"
  },
  {
    "word": "那",
    "pinyin": "nà",
    "part_of_speech": "pronoun",
    "meaning": "that",
    "chapter": 8,
    "source": "hsk1",
    "category": "pronoun"
  },
  {
    "word": "钱",
    "pinyin": "qián",
    "part_of_speech": "noun",
    "meaning": "money",
    "chapter": 8,
    "source": "hsk1",
    "category": "number"
  },
  {
    "word": "儿子",
    "pinyin": "érzi",
    "part_of_speech": "noun",
    "meaning": "son (one's male child)",
    "chapter": 9,
    "source": "hsk1",
    "category": "family"
  },
  {
    "word": "医生",
    "pinyin": "yīshēng",
    "part_of_speech": "noun",
    "meaning": "doctor",
    "chapter": 9,
    "source": "hsk1",
    "category": "person"
  },
  {
    "word": "医院",
    "pinyin": "yīyuàn",
    "part_of_speech": "noun",
    "meaning": "hospital",
    "chapter": 9,
    "source": "hsk1",
    "category": "place"
  },
  {
    "word": "哪儿",
    "pinyin": "nǎr",
    "part_of_speech": "pronoun",
    "meaning": "where",
    "chapter": 9,
    "source": "hsk1",
    "category": "pronoun"
  },
  {
    "word": "在",
    "pinyin": "zài",
    "part_of_speech": "verb",
    "meaning": "at; in; on",
    "chapter": 9,
    "source": "hsk1",
    "category": "direction"
  },
  {
    "word": "小",
    "pinyin": "xiǎo",
    "part_of_speech": "adjective",
    "meaning": "small (in size)",
    "chapter": 9,
    "source": "hsk1",
    "category": "size"
  },
  {
    "word": "工作",
    "pinyin": "gōngzuò",
    "part_of_speech": "verb",
    "meaning": "to work; job",
    "chapter": 9,
    "source": "hsk1",
    "category": "action"
  },
  {
    "word": "椅子",
    "pinyin": "yǐzi",
    "part_of_speech": "noun",
    "meaning": "chair",
    "chapter": 9,
    "source": "hsk1",
    "category": "object"
  },
  {
    "word": "爸爸",
    "pinyin": "bàba",
    "part_of_speech": "noun",
    "meaning": "father",
    "chapter": 9,
    "source": "hsk1",
    "category": "family"
  },
  {
    "word": "狗",
    "pinyin": "gǒu",
    "part_of_speech": "noun",
    "meaning": "dog",
    "chapter": 9,
    "source": "hsk1",
    "category": "animal"
  },
  {
    "word": "猫",
    "pinyin": "māo",
    "part_of_speech": "noun",
    "meaning": "cat",
    "chapter": 9,
    "source": "hsk1",
    "category": "animal"
  },
  {
    "word": "那儿",
    "pinyin": "nàr",
    "part_of_speech": "pronoun",
    "meaning": "there",
    "chapter": 9,
    "source": "hsk1",
    "category": "pronoun"
  },
  {
    "word": "上",
    "pinyin": "shàng",
    "part_of_speech": "noun",
    "meaning": "up, above",
    "chapter": 10,
    "source": "hsk1",
    "category": "direction"
  },
  {
    "word": "下",
    "pinyin": "xià",
    "part_of_speech": "noun",
    "meaning": "down, below, under",
    "chapter": 10,
    "source": "hsk1",
    "category": "direction"
  },
  {
    "word": "前面",
    "pinyin": "qiánmiàn",
    "part_of_speech": "noun",
    "meaning": "front",
    "chapter": 10,
    "source": "hsk1",
    "category": "direction"
  },
  {
    "word": "后面",
    "pinyin": "hòumiàn",
    "part_of_speech": "noun",
    "meaning": "back",
    "chapter": 10,
    "source": "hsk1",
    "category": "direction"
  },
  {
    "word": "和",
    "pinyin": "hé",
    "part_of_speech": "conjunction",
    "meaning": "and; with",
    "chapter": 10,
    "source": "hsk1",
    "category": "grammar"
  },
  {
    "word": "坐",
    "pinyin": "zuò",
    "part_of_speech": "verb",
    "meaning": "to sit, to be seated",
    "chapter": 10,
    "source": "hsk1",
    "category": "movement"
  },
  {
    "word": "本",
    "pinyin": "běn",
    "part_of_speech": "measure_word",
    "meaning": "measure word (books)",
    "chapter": 10,
    "source": "hsk1",
    "category": "grammar"
  },
  {
    "word": "桌子",
    "pinyin": "zhuōzi",
    "part_of_speech": "noun",
    "meaning": "desk, table",
    "chapter": 10,
    "source": "hsk1",
    "category": "object"
  },
  {
    "word": "电脑",
    "pinyin": "diànnǎo",
    "part_of_speech": "noun",
    "meaning": "computer",
    "chapter": 10,
    "source": "hsk1",
    "category": "object"
  },
  {
    "word": "能",
    "pinyin": "néng",
    "part_of_speech": "verb",
    "meaning": "can (permission/ability)",
    "chapter": 10,
    "source": "hsk1",
    "category": "grammar"
  },
  {
    "word": "没有",
    "pinyin": "méiyǒu",
    "part_of_speech": "adverb",
    "meaning": "not have; did not",
    "chapter": 10,
    "source": "hsk1",
    "category": "grammar"
  },
  {
    "word": "这儿",
    "pinyin": "zhèr",
    "part_of_speech": "pronoun",
    "meaning": "here",
    "chapter": 10,
    "source": "hsk1",
    "category": "pronoun"
  },
  {
    "word": "里",
    "pinyin": "lǐ",
    "part_of_speech": "noun",
    "meaning": "inner, inside, interior",
    "chapter": 10,
    "source": "hsk1",
    "category": "direction"
  },
  {
    "word": "现在",
    "pinyin": "xiànzài",
    "part_of_speech": "noun",
    "meaning": "now",
    "chapter": 11,
    "source": "hsk1",
    "category": "time"
  },
  {
    "word": "两",
    "pinyin": "liǎng",
    "part_of_speech": "numeral",
    "meaning": "two (before MW)",
    "chapter": 11,
    "source": "hsk1",
    "category": "number"
  },
  {
    "word": "中午",
    "pinyin": "zhōngwǔ",
    "part_of_speech": "noun",
    "meaning": "noon, midday",
    "chapter": 11,
    "source": "hsk1",
    "category": "time"
  },
  {
    "word": "也",
    "pinyin": "yě",
    "part_of_speech": "adverb",
    "meaning": "also, too",
    "chapter": 11,
    "source": "hsk1",
    "category": "grammar"
  },
  {
    "word": "他们",
    "pinyin": "tāmen",
    "part_of_speech": "pronoun",
    "meaning": "they, them",
    "chapter": 11,
    "source": "hsk1",
    "category": "pronoun"
  },
  {
    "word": "住",
    "pinyin": "zhù",
    "part_of_speech": "verb",
    "meaning": "to live, to stay",
    "chapter": 11,
    "source": "hsk1",
    "category": "action"
  },
  {
    "word": "分",
    "pinyin": "fēn",
    "part_of_speech": "measure_word",
    "meaning": "minute (time-telling)",
    "chapter": 11,
    "source": "hsk1",
    "category": "time"
  },
  {
    "word": "前",
    "pinyin": "qián",
    "part_of_speech": "noun",
    "meaning": "before, earlier than",
    "chapter": 11,
    "source": "hsk1",
    "category": "direction"
  },
  {
    "word": "午",
    "pinyin": "wǔ",
    "part_of_speech": "noun",
    "meaning": "noon (classical)",
    "chapter": 11,
    "source": "hsk1",
    "category": "time"
  },
  {
    "word": "回",
    "pinyin": "huí",
    "part_of_speech": "verb",
    "meaning": "to return, go back",
    "chapter": 11,
    "source": "hsk1",
    "category": "movement"
  },
  {
    "word": "我们",
    "pinyin": "wǒmen",
    "part_of_speech": "pronoun",
    "meaning": "we, us",
    "chapter": 11,
    "source": "hsk1",
    "category": "pronoun"
  },
  {
    "word": "时候",
    "pinyin": "shíhou",
    "part_of_speech": "noun",
    "meaning": "time, moment",
    "chapter": 11,
    "source": "hsk1",
    "category": "time"
  },
  {
    "word": "点",
    "pinyin": "diǎn",
    "part_of_speech": "measure_word",
    "meaning": "o'clock, dot, point",
    "chapter": 11,
    "source": "hsk1",
    "category": "time"
  },
  {
    "word": "电影",
    "pinyin": "diànyǐng",
    "part_of_speech": "noun",
    "meaning": "film, movie",
    "chapter": 11,
    "source": "hsk1",
    "category": "object"
  },
  {
    "word": "下雨",
    "pinyin": "xià yǔ",
    "part_of_speech": "verb",
    "meaning": "to rain",
    "chapter": 12,
    "source": "hsk1",
    "category": "weather"
  },
  {
    "word": "些",
    "pinyin": "xiē",
    "part_of_speech": "measure_word",
    "meaning": "several; some (plural marker, used with 一/这/那)",
    "chapter": 12,
    "source": "hsk1",
    "category": "size"
  },
  {
    "word": "冷",
    "pinyin": "lěng",
    "part_of_speech": "adjective",
    "meaning": "cold",
    "chapter": 12,
    "source": "hsk1",
    "category": "weather"
  },
  {
    "word": "天气",
    "pinyin": "tiānqì",
    "part_of_speech": "noun",
    "meaning": "weather",
    "chapter": 12,
    "source": "hsk1",
    "category": "weather"
  },
  {
    "word": "太",
    "pinyin": "tài",
    "part_of_speech": "adverb",
    "meaning": "too, extremely",
    "chapter": 12,
    "source": "hsk1",
    "category": "grammar"
  },
  {
    "word": "小姐",
    "pinyin": "xiǎojiě",
    "part_of_speech": "noun",
    "meaning": "miss, young lady",
    "chapter": 12,
    "source": "hsk1",
    "category": "person"
  },
  {
    "word": "怎么样",
    "pinyin": "zěnmeyàng",
    "part_of_speech": "pronoun",
    "meaning": "how (about)",
    "chapter": 12,
    "source": "hsk1",
    "category": "pronoun"
  },
  {
    "word": "来",
    "pinyin": "lái",
    "part_of_speech": "verb",
    "meaning": "to come",
    "chapter": 12,
    "source": "hsk1",
    "category": "movement"
  },
  {
    "word": "气",
    "pinyin": "qì",
    "part_of_speech": "noun",
    "meaning": "air, gas, atmosphere",
    "chapter": 12,
    "source": "hsk1",
    "category": "nature"
  },
  {
    "word": "水",
    "pinyin": "shuǐ",
    "part_of_speech": "noun",
    "meaning": "water",
    "chapter": 12,
    "source": "hsk1",
    "category": "food"
  },
  {
    "word": "水果",
    "pinyin": "shuǐguǒ",
    "part_of_speech": "noun",
    "meaning": "fruit",
    "chapter": 12,
    "source": "hsk1",
    "category": "food"
  },
  {
    "word": "热",
    "pinyin": "rè",
    "part_of_speech": "adjective",
    "meaning": "hot",
    "chapter": 12,
    "source": "hsk1",
    "category": "weather"
  },
  {
    "word": "爱",
    "pinyin": "ài",
    "part_of_speech": "verb",
    "meaning": "to love",
    "chapter": 12,
    "source": "hsk1",
    "category": "emotion"
  },
  {
    "word": "身体",
    "pinyin": "shēntǐ",
    "part_of_speech": "noun",
    "meaning": "body, health",
    "chapter": 12,
    "source": "hsk1",
    "category": "body"
  },
  {
    "word": "饭",
    "pinyin": "fàn",
    "part_of_speech": "noun",
    "meaning": "meal, cooked rice",
    "chapter": 12,
    "source": "hsk1",
    "category": "food"
  },
  {
    "word": "喂",
    "pinyin": "wèi",
    "part_of_speech": "interjection",
    "meaning": "hello (on phone)",
    "chapter": 13,
    "source": "hsk1",
    "category": "greeting"
  },
  {
    "word": "学习",
    "pinyin": "xuéxí",
    "part_of_speech": "verb",
    "meaning": "to study, to learn",
    "chapter": 13,
    "source": "hsk1",
    "category": "communication"
  },
  {
    "word": "上午",
    "pinyin": "shàngwǔ",
    "part_of_speech": "noun",
    "meaning": "morning, before noon",
    "chapter": 13,
    "source": "hsk1",
    "category": "time"
  },
  {
    "word": "习",
    "pinyin": "xí",
    "part_of_speech": "verb",
    "meaning": "to practice, to review",
    "chapter": 13,
    "source": "hsk1",
    "category": "communication"
  },
  {
    "word": "喜欢",
    "pinyin": "xǐhuan",
    "part_of_speech": "verb",
    "meaning": "to like, to enjoy",
    "chapter": 13,
    "source": "hsk1",
    "category": "emotion"
  },
  {
    "word": "打电话",
    "pinyin": "dǎ diànhuà",
    "part_of_speech": "verb",
    "meaning": "to make a phone call",
    "chapter": 13,
    "source": "hsk1",
    "category": "communication"
  },
  {
    "word": "日",
    "pinyin": "rì",
    "part_of_speech": "noun",
    "meaning": "sun, day, date",
    "chapter": 13,
    "source": "hsk1",
    "category": "time"
  },
  {
    "word": "电视",
    "pinyin": "diànshì",
    "part_of_speech": "noun",
    "meaning": "television",
    "chapter": 13,
    "source": "hsk1",
    "category": "object"
  },
  {
    "word": "目",
    "pinyin": "mù",
    "part_of_speech": "noun",
    "meaning": "eye",
    "chapter": 13,
    "source": "hsk1",
    "category": "body"
  },
  {
    "word": "睡觉",
    "pinyin": "shuìjiào",
    "part_of_speech": "verb",
    "meaning": "to sleep",
    "chapter": 13,
    "source": "hsk1",
    "category": "action"
  },
  {
    "word": "一点儿",
    "pinyin": "yīdiǎnr",
    "part_of_speech": "adverb",
    "meaning": "a bit; a small amount or degree",
    "chapter": 14,
    "source": "hsk1",
    "category": "size"
  },
  {
    "word": "东西",
    "pinyin": "dōngxi",
    "part_of_speech": "noun",
    "meaning": "thing, stuff",
    "chapter": 14,
    "source": "hsk1",
    "category": "object"
  },
  {
    "word": "先生",
    "pinyin": "xiānsheng",
    "part_of_speech": "noun",
    "meaning": "Mr., Sir",
    "chapter": 14,
    "source": "hsk1",
    "category": "person"
  },
  {
    "word": "分钟",
    "pinyin": "fēnzhōng",
    "part_of_speech": "noun",
    "meaning": "minute (duration)",
    "chapter": 14,
    "source": "hsk1",
    "category": "time"
  },
  {
    "word": "后",
    "pinyin": "hòu",
    "part_of_speech": "noun",
    "meaning": "after, afterwards, later",
    "chapter": 14,
    "source": "hsk1",
    "category": "direction"
  },
  {
    "word": "啊",
    "pinyin": "a",
    "part_of_speech": "particle",
    "meaning": "exclamatory particle",
    "chapter": 14,
    "source": "hsk1",
    "category": "grammar"
  },
  {
    "word": "回来",
    "pinyin": "huílái",
    "part_of_speech": "verb",
    "meaning": "to come back",
    "chapter": 14,
    "source": "hsk1",
    "category": "movement"
  },
  {
    "word": "少",
    "pinyin": "shǎo",
    "part_of_speech": "adjective",
    "meaning": "few; not many (in quantity)",
    "chapter": 14,
    "source": "hsk1",
    "category": "size"
  },
  {
    "word": "开",
    "pinyin": "kāi",
    "part_of_speech": "verb",
    "meaning": "to open; to drive",
    "chapter": 14,
    "source": "hsk1",
    "category": "movement"
  },
  {
    "word": "漂亮",
    "pinyin": "piàoliang",
    "part_of_speech": "adjective",
    "meaning": "beautiful, pretty",
    "chapter": 14,
    "source": "hsk1",
    "category": "emotion"
  },
  {
    "word": "看见",
    "pinyin": "kànjiàn",
    "part_of_speech": "verb",
    "meaning": "to see",
    "chapter": 14,
    "source": "hsk1",
    "category": "action"
  },
  {
    "word": "苹果",
    "pinyin": "píngguǒ",
    "part_of_speech": "noun",
    "meaning": "apple",
    "chapter": 14,
    "source": "hsk1",
    "category": "food"
  },
  {
    "word": "衣服",
    "pinyin": "yīfu",
    "part_of_speech": "noun",
    "meaning": "clothes",
    "chapter": 14,
    "source": "hsk1",
    "category": "object"
  },
  {
    "word": "车",
    "pinyin": "chē",
    "part_of_speech": "noun",
    "meaning": "car, vehicle",
    "chapter": 14,
    "source": "hsk1",
    "category": "object"
  },
  {
    "word": "这些",
    "pinyin": "zhèxiē",
    "part_of_speech": "pronoun",
    "meaning": "these",
    "chapter": 14,
    "source": "hsk1",
    "category": "pronoun"
  },
  {
    "word": "都",
    "pinyin": "dōu",
    "part_of_speech": "adverb",
    "meaning": "both, all",
    "chapter": 14,
    "source": "hsk1",
    "category": "grammar"
  },
  {
    "word": "一起",
    "pinyin": "yìqǐ",
    "part_of_speech": "adverb",
    "meaning": "together",
    "chapter": 15,
    "source": "hsk1",
    "category": "grammar"
  },
  {
    "word": "出",
    "pinyin": "chū",
    "part_of_speech": "verb",
    "meaning": "to go out, to exit",
    "chapter": 15,
    "source": "hsk1",
    "category": "movement"
  },
  {
    "word": "出租车",
    "pinyin": "chūzūchē",
    "part_of_speech": "noun",
    "meaning": "taxi, cab",
    "chapter": 15,
    "source": "hsk1",
    "category": "object"
  },
  {
    "word": "听",
    "pinyin": "tīng",
    "part_of_speech": "verb",
    "meaning": "to listen",
    "chapter": 15,
    "source": "hsk1",
    "category": "communication"
  },
  {
    "word": "大学",
    "pinyin": "dàxué",
    "part_of_speech": "noun",
    "meaning": "college, university",
    "chapter": 15,
    "source": "hsk1",
    "category": "place"
  },
  {
    "word": "年",
    "pinyin": "nián",
    "part_of_speech": "noun",
    "meaning": "year",
    "chapter": 15,
    "source": "hsk1",
    "category": "time"
  },
  {
    "word": "认识",
    "pinyin": "rènshi",
    "part_of_speech": "verb",
    "meaning": "to meet, to know",
    "chapter": 15,
    "source": "hsk1",
    "category": "communication"
  },
  {
    "word": "飞",
    "pinyin": "fēi",
    "part_of_speech": "verb",
    "meaning": "to fly",
    "chapter": 15,
    "source": "hsk1",
    "category": "movement"
  },
  {
    "word": "飞机",
    "pinyin": "fēijī",
    "part_of_speech": "noun",
    "meaning": "airplane",
    "chapter": 15,
    "source": "hsk1",
    "category": "object"
  },
  {
    "word": "饭店",
    "pinyin": "fàndiàn",
    "part_of_speech": "noun",
    "meaning": "hotel, restaurant",
    "chapter": 15,
    "source": "hsk1",
    "category": "place"
  },
  {
    "word": "高兴",
    "pinyin": "gāoxìng",
    "part_of_speech": "adjective",
    "meaning": "glad, happy",
    "chapter": 15,
    "source": "hsk1",
    "category": "emotion"
  },
  {
    "word": "你好吗",
    "pinyin": "nǐ hǎo ma",
    "part_of_speech": "phrase",
    "meaning": "How are you?",
    "chapter": -3,
    "source": "compound",
    "category": "greeting"
  },
  {
    "word": "中国人",
    "pinyin": "Zhōngguó rén",
    "part_of_speech": "noun",
    "meaning": "Chinese person",
    "chapter": -3,
    "source": "compound",
    "category": "country"
  },
  {
    "word": "美国人",
    "pinyin": "Měiguó rén",
    "part_of_speech": "noun",
    "meaning": "American person",
    "chapter": -3,
    "source": "compound",
    "category": "country"
  },
  {
    "word": "你是学生吗",
    "pinyin": "nǐ shì xuéshēng ma",
    "part_of_speech": "phrase",
    "meaning": "Are you a student?",
    "chapter": -3,
    "source": "compound",
    "category": "person"
  },
  {
    "word": "我是学生",
    "pinyin": "wǒ shì xuéshēng",
    "part_of_speech": "phrase",
    "meaning": "I am a student",
    "chapter": -3,
    "source": "compound",
    "category": "person"
  },
  {
    "word": "他是谁",
    "pinyin": "tā shì shéi",
    "part_of_speech": "phrase",
    "meaning": "Who is he?",
    "chapter": -4,
    "source": "compound",
    "category": "pronoun"
  },
  {
    "word": "你的名字",
    "pinyin": "nǐ de míngzi",
    "part_of_speech": "phrase",
    "meaning": "your name",
    "chapter": -4,
    "source": "compound",
    "category": "pronoun"
  },
  {
    "word": "我的朋友",
    "pinyin": "wǒ de péngyǒu",
    "part_of_speech": "phrase",
    "meaning": "my friend",
    "chapter": -4,
    "source": "compound",
    "category": "person"
  },
  {
    "word": "哪国人",
    "pinyin": "nǎ guó rén",
    "part_of_speech": "phrase",
    "meaning": "which nationality?",
    "chapter": -4,
    "source": "compound",
    "category": "country"
  },
  {
    "word": "你几岁",
    "pinyin": "nǐ jǐ suì",
    "part_of_speech": "phrase",
    "meaning": "How old are you?",
    "chapter": -5,
    "source": "compound",
    "category": "time"
  },
  {
    "word": "多大",
    "pinyin": "duō dà",
    "part_of_speech": "phrase",
    "meaning": "how old? (age)",
    "chapter": -5,
    "source": "compound",
    "category": "time"
  },
  {
    "word": "大家好",
    "pinyin": "dàjiā hǎo",
    "part_of_speech": "phrase",
    "meaning": "Hello everyone!",
    "chapter": -5,
    "source": "compound",
    "category": "greeting"
  },
  {
    "word": "有没有",
    "pinyin": "yǒu méi yǒu",
    "part_of_speech": "phrase",
    "meaning": "do you have...?",
    "chapter": -5,
    "source": "compound",
    "category": "grammar"
  },
  {
    "word": "很好",
    "pinyin": "hěn hǎo",
    "part_of_speech": "phrase",
    "meaning": "very good",
    "chapter": -6,
    "source": "compound",
    "category": "emotion"
  },
  {
    "word": "我很好",
    "pinyin": "wǒ hěn hǎo",
    "part_of_speech": "phrase",
    "meaning": "I'm fine",
    "chapter": -6,
    "source": "compound",
    "category": "emotion"
  },
  {
    "word": "会说汉语",
    "pinyin": "huì shuō Hànyǔ",
    "part_of_speech": "phrase",
    "meaning": "can speak Chinese",
    "chapter": -6,
    "source": "compound",
    "category": "communication"
  },
  {
    "word": "怎么说",
    "pinyin": "zěnme shuō",
    "part_of_speech": "phrase",
    "meaning": "how to say?",
    "chapter": -6,
    "source": "compound",
    "category": "communication"
  },
  {
    "word": "怎么写",
    "pinyin": "zěnme xiě",
    "part_of_speech": "phrase",
    "meaning": "how to write?",
    "chapter": -6,
    "source": "compound",
    "category": "communication"
  },
  {
    "word": "请问",
    "pinyin": "qǐngwèn",
    "part_of_speech": "phrase",
    "meaning": "excuse me (asking)",
    "chapter": -7,
    "source": "compound",
    "category": "communication"
  },
  {
    "word": "今天几号",
    "pinyin": "jīntiān jǐ hào",
    "part_of_speech": "phrase",
    "meaning": "What's today's date?",
    "chapter": -7,
    "source": "compound",
    "category": "time"
  },
  {
    "word": "去学校",
    "pinyin": "qù xuéxiào",
    "part_of_speech": "phrase",
    "meaning": "go to school",
    "chapter": -7,
    "source": "compound",
    "category": "place"
  },
  {
    "word": "星期几",
    "pinyin": "xīngqī jǐ",
    "part_of_speech": "phrase",
    "meaning": "which day of week?",
    "chapter": -7,
    "source": "compound",
    "category": "time"
  },
  {
    "word": "多少钱",
    "pinyin": "duōshao qián",
    "part_of_speech": "phrase",
    "meaning": "How much (money)?",
    "chapter": -8,
    "source": "compound",
    "category": "number"
  },
  {
    "word": "这个",
    "pinyin": "zhège",
    "part_of_speech": "pronoun",
    "meaning": "this one",
    "chapter": -8,
    "source": "compound",
    "category": "pronoun"
  },
  {
    "word": "那个",
    "pinyin": "nàge",
    "part_of_speech": "pronoun",
    "meaning": "that one",
    "chapter": -8,
    "source": "compound",
    "category": "pronoun"
  },
  {
    "word": "喝茶",
    "pinyin": "hē chá",
    "part_of_speech": "phrase",
    "meaning": "drink tea",
    "chapter": -8,
    "source": "compound",
    "category": "food"
  },
  {
    "word": "想买",
    "pinyin": "xiǎng mǎi",
    "part_of_speech": "phrase",
    "meaning": "want to buy",
    "chapter": -8,
    "source": "compound",
    "category": "action"
  },
  {
    "word": "在哪儿",
    "pinyin": "zài nǎr",
    "part_of_speech": "phrase",
    "meaning": "where is...?",
    "chapter": -9,
    "source": "compound",
    "category": "direction"
  },
  {
    "word": "你在哪儿",
    "pinyin": "nǐ zài nǎr",
    "part_of_speech": "phrase",
    "meaning": "Where are you?",
    "chapter": -9,
    "source": "compound",
    "category": "direction"
  },
  {
    "word": "在家",
    "pinyin": "zài jiā",
    "part_of_speech": "phrase",
    "meaning": "at home",
    "chapter": -9,
    "source": "compound",
    "category": "family"
  },
  {
    "word": "坐下",
    "pinyin": "zuò xià",
    "part_of_speech": "phrase",
    "meaning": "sit down",
    "chapter": -10,
    "source": "compound",
    "category": "movement"
  },
  {
    "word": "上下",
    "pinyin": "shàng xià",
    "part_of_speech": "noun",
    "meaning": "up and down",
    "chapter": -10,
    "source": "compound",
    "category": "direction"
  },
  {
    "word": "在上面",
    "pinyin": "zài shàngmiàn",
    "part_of_speech": "phrase",
    "meaning": "on top of",
    "chapter": -10,
    "source": "compound",
    "category": "direction"
  },
  {
    "word": "在里面",
    "pinyin": "zài lǐmiàn",
    "part_of_speech": "phrase",
    "meaning": "to be inside",
    "chapter": -10,
    "source": "compound",
    "category": "direction"
  },
  {
    "word": "几点",
    "pinyin": "jǐ diǎn",
    "part_of_speech": "phrase",
    "meaning": "what time?",
    "chapter": -11,
    "source": "compound",
    "category": "time"
  },
  {
    "word": "回家",
    "pinyin": "huí jiā",
    "part_of_speech": "phrase",
    "meaning": "go home",
    "chapter": -11,
    "source": "compound",
    "category": "family"
  },
  {
    "word": "几点回家",
    "pinyin": "jǐ diǎn huí jiā",
    "part_of_speech": "phrase",
    "meaning": "What time go home?",
    "chapter": -11,
    "source": "compound",
    "category": "family"
  },
  {
    "word": "天气怎么样",
    "pinyin": "tiānqì zěnmeyàng",
    "part_of_speech": "phrase",
    "meaning": "How's the weather?",
    "chapter": -12,
    "source": "compound",
    "category": "weather"
  },
  {
    "word": "喝水",
    "pinyin": "hē shuǐ",
    "part_of_speech": "phrase",
    "meaning": "drink water",
    "chapter": -12,
    "source": "compound",
    "category": "food"
  },
  {
    "word": "太冷了",
    "pinyin": "tài lěng le",
    "part_of_speech": "phrase",
    "meaning": "too cold!",
    "chapter": -12,
    "source": "compound",
    "category": "weather"
  },
  {
    "word": "太热了",
    "pinyin": "tài rè le",
    "part_of_speech": "phrase",
    "meaning": "too hot!",
    "chapter": -12,
    "source": "compound",
    "category": "weather"
  },
  {
    "word": "我爱你",
    "pinyin": "wǒ ài nǐ",
    "part_of_speech": "phrase",
    "meaning": "I love you",
    "chapter": -12,
    "source": "compound",
    "category": "emotion"
  },
  {
    "word": "吃饭",
    "pinyin": "chī fàn",
    "part_of_speech": "verb",
    "meaning": "to eat (a meal)",
    "chapter": 11,
    "source": "hsk1",
    "category": "food"
  },
  {
    "word": "看电视",
    "pinyin": "kàn diànshì",
    "part_of_speech": "phrase",
    "meaning": "watch TV",
    "chapter": -13,
    "source": "compound",
    "category": "action"
  },
  {
    "word": "喜欢吃",
    "pinyin": "xǐhuan chī",
    "part_of_speech": "phrase",
    "meaning": "like to eat",
    "chapter": -13,
    "source": "compound",
    "category": "food"
  },
  {
    "word": "开车",
    "pinyin": "kāi chē",
    "part_of_speech": "phrase",
    "meaning": "drive (a car)",
    "chapter": -14,
    "source": "compound",
    "category": "movement"
  },
  {
    "word": "买东西",
    "pinyin": "mǎi dōngxi",
    "part_of_speech": "phrase",
    "meaning": "go shopping",
    "chapter": -14,
    "source": "compound",
    "category": "action"
  },
  {
    "word": "很漂亮",
    "pinyin": "hěn piàoliang",
    "part_of_speech": "phrase",
    "meaning": "very beautiful",
    "chapter": -14,
    "source": "compound",
    "category": "emotion"
  },
  {
    "word": "坐飞机",
    "pinyin": "zuò fēijī",
    "part_of_speech": "phrase",
    "meaning": "take a plane",
    "chapter": -15,
    "source": "compound",
    "category": "movement"
  },
  {
    "word": "坐出租车",
    "pinyin": "zuò chūzūchē",
    "part_of_speech": "phrase",
    "meaning": "take a taxi",
    "chapter": -15,
    "source": "compound",
    "category": "movement"
  },
  {
    "word": "一起去",
    "pinyin": "yìqǐ qù",
    "part_of_speech": "phrase",
    "meaning": "go together",
    "chapter": -15,
    "source": "compound",
    "category": "movement"
  },
  {
    "word": "认识你很高兴",
    "pinyin": "rènshi nǐ hěn gāoxìng",
    "part_of_speech": "phrase",
    "meaning": "Nice to meet you",
    "chapter": -15,
    "source": "compound",
    "category": "emotion"
  },
  {
    "word": "很高兴",
    "pinyin": "hěn gāoxìng",
    "part_of_speech": "phrase",
    "meaning": "very happy",
    "chapter": -15,
    "source": "compound",
    "category": "emotion"
  },
  {
    "word": "早上",
    "pinyin": "zǎoshang",
    "part_of_speech": "noun",
    "meaning": "morning, early morning",
    "chapter": -8,
    "source": "hsk1",
    "category": "time"
  },
  {
    "word": "晚上",
    "pinyin": "wǎnshang",
    "part_of_speech": "noun",
    "meaning": "evening, night",
    "chapter": -8,
    "source": "hsk1",
    "category": "time"
  },
  {
    "word": "高",
    "pinyin": "gāo",
    "part_of_speech": "adjective",
    "meaning": "tall, high",
    "chapter": -16,
    "source": "hsk1",
    "category": "size"
  },
  {
    "word": "矮",
    "pinyin": "ǎi",
    "part_of_speech": "adjective",
    "meaning": "short (height)",
    "chapter": -16,
    "source": "hsk1",
    "category": "size"
  },
  {
    "word": "外",
    "pinyin": "wài",
    "part_of_speech": "noun",
    "meaning": "outer, external",
    "chapter": -10,
    "source": "hsk1",
    "category": "direction"
  },
  {
    "word": "左",
    "pinyin": "zuǒ",
    "part_of_speech": "noun",
    "meaning": "left",
    "chapter": -10,
    "source": "hsk1",
    "category": "direction"
  },
  {
    "word": "右",
    "pinyin": "yòu",
    "part_of_speech": "noun",
    "meaning": "right",
    "chapter": -10,
    "source": "hsk1",
    "category": "direction"
  },
  {
    "word": "上面",
    "pinyin": "shàngmiàn",
    "part_of_speech": "noun",
    "meaning": "above, on top of",
    "chapter": -10,
    "source": "hsk1",
    "category": "direction"
  },
  {
    "word": "下面",
    "pinyin": "xiàmiàn",
    "part_of_speech": "noun",
    "meaning": "below, under",
    "chapter": 9,
    "source": "hsk1",
    "category": "direction"
  },
  {
    "word": "里面",
    "pinyin": "lǐmiàn",
    "part_of_speech": "noun",
    "meaning": "inside",
    "chapter": -10,
    "source": "hsk1",
    "category": "direction"
  },
  {
    "word": "外面",
    "pinyin": "wàimiàn",
    "part_of_speech": "noun",
    "meaning": "outside",
    "chapter": -10,
    "source": "hsk1",
    "category": "direction"
  },
  {
    "word": "左边",
    "pinyin": "zuǒbiān",
    "part_of_speech": "noun",
    "meaning": "left side",
    "chapter": -10,
    "source": "hsk1",
    "category": "direction"
  },
  {
    "word": "右边",
    "pinyin": "yòubiān",
    "part_of_speech": "noun",
    "meaning": "right side",
    "chapter": -10,
    "source": "hsk1",
    "category": "direction"
  },
  {
    "word": "旁边",
    "pinyin": "pángbiān",
    "part_of_speech": "noun",
    "meaning": "beside, next to",
    "chapter": -10,
    "source": "hsk1",
    "category": "direction"
  },
  {
    "word": "对面",
    "pinyin": "duìmiàn",
    "part_of_speech": "noun",
    "meaning": "opposite, across from",
    "chapter": -10,
    "source": "hsk1",
    "category": "direction"
  },
  {
    "word": "在下面",
    "pinyin": "zài xiàmiàn",
    "part_of_speech": "phrase",
    "meaning": "underneath, below",
    "chapter": -10,
    "source": "compound",
    "category": "direction"
  },
  {
    "word": "在前面",
    "pinyin": "zài qiánmiàn",
    "part_of_speech": "phrase",
    "meaning": "in front of",
    "chapter": -10,
    "source": "compound",
    "category": "direction"
  },
  {
    "word": "在后面",
    "pinyin": "zài hòumiàn",
    "part_of_speech": "phrase",
    "meaning": "behind",
    "chapter": -10,
    "source": "compound",
    "category": "direction"
  },
  {
    "word": "在外面",
    "pinyin": "zài wàimiàn",
    "part_of_speech": "phrase",
    "meaning": "to be outside",
    "chapter": -10,
    "source": "compound",
    "category": "direction"
  },
  {
    "word": "在旁边",
    "pinyin": "zài pángbiān",
    "part_of_speech": "phrase",
    "meaning": "to be beside",
    "chapter": -10,
    "source": "compound",
    "category": "direction"
  },
  {
    "word": "在对面",
    "pinyin": "zài duìmiàn",
    "part_of_speech": "phrase",
    "meaning": "to be across from",
    "chapter": -10,
    "source": "compound",
    "category": "direction"
  },
  {
    "word": "在左边",
    "pinyin": "zài zuǒbiān",
    "part_of_speech": "phrase",
    "meaning": "on the left",
    "chapter": -10,
    "source": "compound",
    "category": "direction"
  },
  {
    "word": "在右边",
    "pinyin": "zài yòubiān",
    "part_of_speech": "phrase",
    "meaning": "on the right",
    "chapter": -10,
    "source": "compound",
    "category": "direction"
  },
  {
    "word": "这儿有人吗",
    "pinyin": "zhèr yǒu rén ma",
    "part_of_speech": "phrase",
    "meaning": "Is anyone here? / Is this seat taken?",
    "chapter": -10,
    "source": "compound",
    "category": "place"
  },
  {
    "word": "凌晨",
    "pinyin": "língchén",
    "part_of_speech": "noun",
    "meaning": "wee hours (before dawn)",
    "chapter": -8,
    "source": "hsk1",
    "category": "time"
  },
  {
    "word": "地",
    "pinyin": "de",
    "part_of_speech": "particle",
    "meaning": "adverbial marker",
    "chapter": 16,
    "source": "hsk1",
    "category": "grammar"
  },
  {
    "word": "得",
    "pinyin": "de",
    "part_of_speech": "particle",
    "meaning": "complement marker",
    "chapter": 16,
    "source": "hsk1",
    "category": "grammar"
  },
  {
    "word": "着",
    "pinyin": "zhe",
    "part_of_speech": "particle",
    "meaning": "ongoing action",
    "chapter": 16,
    "source": "hsk1",
    "category": "grammar"
  },
  {
    "word": "过",
    "pinyin": "guo",
    "part_of_speech": "particle",
    "meaning": "have done before",
    "chapter": 16,
    "source": "hsk1",
    "category": "grammar"
  },
  {
    "word": "吧",
    "pinyin": "ba",
    "part_of_speech": "particle",
    "meaning": "suggestion; softening",
    "chapter": 16,
    "source": "hsk1",
    "category": "grammar"
  },
  {
    "word": "呀",
    "pinyin": "ya",
    "part_of_speech": "particle",
    "meaning": "exclamation variant",
    "chapter": 16,
    "source": "hsk1",
    "category": "grammar"
  },
  {
    "word": "哇",
    "pinyin": "wa",
    "part_of_speech": "particle",
    "meaning": "surprise / admiration",
    "chapter": 16,
    "source": "hsk1",
    "category": "grammar"
  },
  {
    "word": "啦",
    "pinyin": "la",
    "part_of_speech": "particle",
    "meaning": "emphasis; change",
    "chapter": 16,
    "source": "hsk1",
    "category": "grammar"
  },
  {
    "word": "嘛",
    "pinyin": "ma",
    "part_of_speech": "particle",
    "meaning": "obviousness / persuasion",
    "chapter": 16,
    "source": "hsk1",
    "category": "grammar"
  },
  {
    "word": "呐",
    "pinyin": "na",
    "part_of_speech": "particle",
    "meaning": "exclamatory emphasis",
    "chapter": 16,
    "source": "hsk1",
    "category": "grammar"
  },
  {
    "word": "或者",
    "pinyin": "huòzhě",
    "part_of_speech": "conjunction",
    "meaning": "or",
    "chapter": 16,
    "source": "hsk1",
    "category": "grammar"
  },
  {
    "word": "还是",
    "pinyin": "háishì",
    "part_of_speech": "conjunction",
    "meaning": "or (in questions)",
    "chapter": 16,
    "source": "hsk1",
    "category": "grammar"
  },
  {
    "word": "但是",
    "pinyin": "dànshì",
    "part_of_speech": "conjunction",
    "meaning": "but (formal)",
    "chapter": 16,
    "source": "hsk1",
    "category": "grammar"
  },
  {
    "word": "可是",
    "pinyin": "kěshì",
    "part_of_speech": "conjunction",
    "meaning": "but (casual)",
    "chapter": 16,
    "source": "hsk1",
    "category": "grammar"
  },
  {
    "word": "因为",
    "pinyin": "yīnwèi",
    "part_of_speech": "conjunction",
    "meaning": "because; because of",
    "chapter": 16,
    "source": "hsk1",
    "category": "grammar"
  },
  {
    "word": "所以",
    "pinyin": "suǒyǐ",
    "part_of_speech": "conjunction",
    "meaning": "so, therefore",
    "chapter": 16,
    "source": "hsk1",
    "category": "grammar"
  },
  {
    "word": "如果",
    "pinyin": "rúguǒ",
    "part_of_speech": "conjunction",
    "meaning": "if",
    "chapter": 16,
    "source": "hsk1",
    "category": "grammar"
  },
  {
    "word": "虽然",
    "pinyin": "suīrán",
    "part_of_speech": "conjunction",
    "meaning": "although",
    "chapter": 16,
    "source": "hsk1",
    "category": "grammar"
  },
  {
    "word": "而且",
    "pinyin": "érqiě",
    "part_of_speech": "conjunction",
    "meaning": "and moreover",
    "chapter": 16,
    "source": "hsk1",
    "category": "grammar"
  },
  {
    "word": "从",
    "pinyin": "cóng",
    "part_of_speech": "preposition",
    "meaning": "from",
    "chapter": 16,
    "source": "hsk1",
    "category": "grammar"
  },
  {
    "word": "到",
    "pinyin": "dào",
    "part_of_speech": "preposition",
    "meaning": "to / until",
    "chapter": 16,
    "source": "hsk1",
    "category": "grammar"
  },
  {
    "word": "给",
    "pinyin": "gěi",
    "part_of_speech": "preposition",
    "meaning": "give; to/for",
    "chapter": 16,
    "source": "hsk1",
    "category": "grammar"
  },
  {
    "word": "跟",
    "pinyin": "gēn",
    "part_of_speech": "preposition",
    "meaning": "with",
    "chapter": 16,
    "source": "hsk1",
    "category": "grammar"
  },
  {
    "word": "用",
    "pinyin": "yòng",
    "part_of_speech": "preposition",
    "meaning": "using / with",
    "chapter": 16,
    "source": "hsk1",
    "category": "action"
  },
  {
    "word": "对",
    "pinyin": "duì",
    "part_of_speech": "preposition",
    "meaning": "toward / regarding",
    "chapter": 16,
    "source": "hsk1",
    "category": "grammar"
  },
  {
    "word": "向",
    "pinyin": "xiàng",
    "part_of_speech": "preposition",
    "meaning": "toward / facing",
    "chapter": 16,
    "source": "hsk1",
    "category": "direction"
  },
  {
    "word": "往",
    "pinyin": "wǎng",
    "part_of_speech": "preposition",
    "meaning": "toward (going)",
    "chapter": 16,
    "source": "hsk1",
    "category": "direction"
  },
  {
    "word": "比",
    "pinyin": "bǐ",
    "part_of_speech": "preposition",
    "meaning": "compared with / than",
    "chapter": 16,
    "source": "hsk1",
    "category": "grammar"
  },
  {
    "word": "把",
    "pinyin": "bǎ",
    "part_of_speech": "preposition",
    "meaning": "object marker",
    "chapter": 16,
    "source": "hsk1",
    "category": "grammar"
  },
  {
    "word": "被",
    "pinyin": "bèi",
    "part_of_speech": "preposition",
    "meaning": "passive marker",
    "chapter": 16,
    "source": "hsk1",
    "category": "grammar"
  },
  {
    "word": "离",
    "pinyin": "lí",
    "part_of_speech": "preposition",
    "meaning": "from / away from",
    "chapter": 16,
    "source": "hsk1",
    "category": "direction"
  },
  {
    "word": "按",
    "pinyin": "àn",
    "part_of_speech": "preposition",
    "meaning": "per, following",
    "chapter": 16,
    "source": "hsk1",
    "category": "grammar"
  },
  {
    "word": "照",
    "pinyin": "zhào",
    "part_of_speech": "preposition",
    "meaning": "as per",
    "chapter": 16,
    "source": "hsk1",
    "category": "grammar"
  },
  {
    "word": "为",
    "pinyin": "wèi",
    "part_of_speech": "preposition",
    "meaning": "for (sake of)",
    "chapter": 16,
    "source": "hsk1",
    "category": "grammar"
  },
  {
    "word": "为了",
    "pinyin": "wèile",
    "part_of_speech": "preposition",
    "meaning": "in order to",
    "chapter": 16,
    "source": "hsk1",
    "category": "grammar"
  },
  {
    "word": "关于",
    "pinyin": "guānyú",
    "part_of_speech": "preposition",
    "meaning": "about / regarding",
    "chapter": 16,
    "source": "hsk1",
    "category": "grammar"
  },
  {
    "word": "自",
    "pinyin": "zì",
    "part_of_speech": "preposition",
    "meaning": "from / since",
    "chapter": 16,
    "source": "hsk1",
    "category": "grammar"
  },
  {
    "word": "以",
    "pinyin": "yǐ",
    "part_of_speech": "preposition",
    "meaning": "by means of / with",
    "chapter": 16,
    "source": "hsk1",
    "category": "grammar"
  },
  {
    "word": "因",
    "pinyin": "yīn",
    "part_of_speech": "preposition",
    "meaning": "due to",
    "chapter": 16,
    "source": "hsk1",
    "category": "grammar"
  },
  {
    "word": "由",
    "pinyin": "yóu",
    "part_of_speech": "preposition",
    "meaning": "by; via",
    "chapter": 16,
    "source": "hsk1",
    "category": "grammar"
  },
  {
    "word": "经",
    "pinyin": "jīng",
    "part_of_speech": "preposition",
    "meaning": "through / via",
    "chapter": 16,
    "source": "hsk1",
    "category": "grammar"
  },
  {
    "word": "经由",
    "pinyin": "jīngyóu",
    "part_of_speech": "preposition",
    "meaning": "via / by way of",
    "chapter": 16,
    "source": "hsk1",
    "category": "grammar"
  },
  {
    "word": "朝",
    "pinyin": "cháo",
    "part_of_speech": "preposition",
    "meaning": "toward (facing)",
    "chapter": 16,
    "source": "hsk1",
    "category": "direction"
  },
  {
    "word": "对于",
    "pinyin": "duìyú",
    "part_of_speech": "preposition",
    "meaning": "regarding",
    "chapter": 16,
    "source": "hsk1",
    "category": "grammar"
  },
  {
    "word": "至于",
    "pinyin": "zhìyú",
    "part_of_speech": "preposition",
    "meaning": "as for",
    "chapter": 16,
    "source": "hsk1",
    "category": "grammar"
  },
  {
    "word": "替",
    "pinyin": "tì",
    "part_of_speech": "preposition",
    "meaning": "in place of, for",
    "chapter": 16,
    "source": "hsk1",
    "category": "grammar"
  },
  {
    "word": "帮",
    "pinyin": "bāng",
    "part_of_speech": "preposition",
    "meaning": "for (helping)",
    "chapter": 16,
    "source": "hsk1",
    "category": "grammar"
  },
  {
    "word": "根据",
    "pinyin": "gēnjù",
    "part_of_speech": "preposition",
    "meaning": "based on",
    "chapter": 16,
    "source": "hsk1",
    "category": "grammar"
  },
  {
    "word": "依据",
    "pinyin": "yījù",
    "part_of_speech": "preposition",
    "meaning": "based on; per",
    "chapter": 16,
    "source": "hsk1",
    "category": "grammar"
  },
  {
    "word": "本着",
    "pinyin": "běnzhe",
    "part_of_speech": "preposition",
    "meaning": "in line with",
    "chapter": 16,
    "source": "hsk1",
    "category": "grammar"
  },
  {
    "word": "卖",
    "pinyin": "mài",
    "part_of_speech": "verb",
    "meaning": "to sell",
    "chapter": 16,
    "source": "hsk1",
    "category": "action"
  },
  {
    "word": "拿",
    "pinyin": "ná",
    "part_of_speech": "verb",
    "meaning": "to take / hold",
    "chapter": 16,
    "source": "hsk1",
    "category": "action"
  },
  {
    "word": "放",
    "pinyin": "fàng",
    "part_of_speech": "verb",
    "meaning": "to put / place",
    "chapter": 16,
    "source": "hsk1",
    "category": "action"
  },
  {
    "word": "关",
    "pinyin": "guān",
    "part_of_speech": "verb",
    "meaning": "to close",
    "chapter": 16,
    "source": "hsk1",
    "category": "action"
  },
  {
    "word": "找",
    "pinyin": "zhǎo",
    "part_of_speech": "verb",
    "meaning": "to find",
    "chapter": 16,
    "source": "hsk1",
    "category": "action"
  },
  {
    "word": "教",
    "pinyin": "jiào",
    "part_of_speech": "verb",
    "meaning": "to teach",
    "chapter": 16,
    "source": "hsk1",
    "category": "communication"
  },
  {
    "word": "者",
    "pinyin": "zhě",
    "part_of_speech": "noun",
    "meaning": "-er (doer suffix)",
    "chapter": 16,
    "source": "hsk1",
    "category": "person"
  },
  {
    "word": "师",
    "pinyin": "shī",
    "part_of_speech": "noun",
    "meaning": "specialist",
    "chapter": 16,
    "source": "hsk1",
    "category": "person"
  },
  {
    "word": "员",
    "pinyin": "yuán",
    "part_of_speech": "noun",
    "meaning": "member / staff",
    "chapter": 16,
    "source": "hsk1",
    "category": "person"
  },
  {
    "word": "生",
    "pinyin": "shēng",
    "part_of_speech": "noun",
    "meaning": "student; life",
    "chapter": 16,
    "source": "hsk1",
    "category": "person"
  },
  {
    "word": "学",
    "pinyin": "xué",
    "part_of_speech": "noun",
    "meaning": "study / learning",
    "chapter": 16,
    "source": "hsk1",
    "category": "other"
  },
  {
    "word": "学家",
    "pinyin": "xuéjiā",
    "part_of_speech": "noun",
    "meaning": "scholar",
    "chapter": 16,
    "source": "hsk1",
    "category": "person"
  },
  {
    "word": "教师",
    "pinyin": "jiàoshī",
    "part_of_speech": "noun",
    "meaning": "teacher (formal)",
    "chapter": 16,
    "source": "hsk1",
    "category": "person"
  },
  {
    "word": "馆",
    "pinyin": "guǎn",
    "part_of_speech": "noun",
    "meaning": "hall; institution",
    "chapter": 16,
    "source": "hsk1",
    "category": "place"
  },
  {
    "word": "室",
    "pinyin": "shì",
    "part_of_speech": "noun",
    "meaning": "room",
    "chapter": 16,
    "source": "hsk1",
    "category": "place"
  },
  {
    "word": "厂",
    "pinyin": "chǎng",
    "part_of_speech": "noun",
    "meaning": "factory / plant",
    "chapter": 16,
    "source": "hsk1",
    "category": "place"
  },
  {
    "word": "店",
    "pinyin": "diàn",
    "part_of_speech": "noun",
    "meaning": "shop / store",
    "chapter": 16,
    "source": "hsk1",
    "category": "place"
  },
  {
    "word": "城",
    "pinyin": "chéng",
    "part_of_speech": "noun",
    "meaning": "city",
    "chapter": 16,
    "source": "hsk1",
    "category": "place"
  },
  {
    "word": "村",
    "pinyin": "cūn",
    "part_of_speech": "noun",
    "meaning": "village",
    "chapter": 16,
    "source": "hsk1",
    "category": "place"
  },
  {
    "word": "体",
    "pinyin": "tǐ",
    "part_of_speech": "noun",
    "meaning": "body / system",
    "chapter": 16,
    "source": "hsk1",
    "category": "body"
  },
  {
    "word": "形",
    "pinyin": "xíng",
    "part_of_speech": "noun",
    "meaning": "form / type",
    "chapter": 16,
    "source": "hsk1",
    "category": "other"
  },
  {
    "word": "法",
    "pinyin": "fǎ",
    "part_of_speech": "noun",
    "meaning": "law / method",
    "chapter": 16,
    "source": "hsk1",
    "category": "other"
  },
  {
    "word": "学科",
    "pinyin": "xuékē",
    "part_of_speech": "noun",
    "meaning": "field of study",
    "chapter": 16,
    "source": "hsk1",
    "category": "other"
  },
  {
    "word": "文",
    "pinyin": "wén",
    "part_of_speech": "noun",
    "meaning": "culture / writing",
    "chapter": 16,
    "source": "hsk1",
    "category": "other"
  },
  {
    "word": "机",
    "pinyin": "jī",
    "part_of_speech": "noun",
    "meaning": "machine / device",
    "chapter": 16,
    "source": "hsk1",
    "category": "object"
  },
  {
    "word": "物",
    "pinyin": "wù",
    "part_of_speech": "noun",
    "meaning": "object / thing",
    "chapter": 16,
    "source": "hsk1",
    "category": "object"
  },
  {
    "word": "中间",
    "pinyin": "zhōngjiān",
    "part_of_speech": "noun",
    "meaning": "middle; between",
    "chapter": 16,
    "source": "hsk1",
    "category": "direction"
  },
  {
    "word": "北京",
    "pinyin": "Běijīng",
    "part_of_speech": "noun",
    "meaning": "Beijing (northern capital)",
    "chapter": 17,
    "source": "hsk1",
    "category": "city"
  },
  {
    "word": "上海",
    "pinyin": "Shànghǎi",
    "part_of_speech": "noun",
    "meaning": "Shanghai (on the sea)",
    "chapter": 17,
    "source": "hsk1",
    "category": "city"
  },
  {
    "word": "香港",
    "pinyin": "Xiānggǎng",
    "part_of_speech": "noun",
    "meaning": "Hong Kong (fragrant harbor)",
    "chapter": 17,
    "source": "hsk1",
    "category": "city"
  },
  {
    "word": "纽约",
    "pinyin": "Niǔyuē",
    "part_of_speech": "noun",
    "meaning": "New York City",
    "chapter": 17,
    "source": "hsk1",
    "category": "city"
  },
  {
    "word": "洛杉矶",
    "pinyin": "Luòshānjī",
    "part_of_speech": "noun",
    "meaning": "Los Angeles",
    "chapter": 17,
    "source": "hsk1",
    "category": "city"
  },
  {
    "word": "波士顿",
    "pinyin": "Bōshìdùn",
    "part_of_speech": "noun",
    "meaning": "Boston",
    "chapter": 17,
    "source": "hsk1",
    "category": "city"
  },
  {
    "word": "巴尔的摩",
    "pinyin": "Bā'ěrdìmó",
    "part_of_speech": "noun",
    "meaning": "Baltimore",
    "chapter": 17,
    "source": "hsk1",
    "category": "city"
  },
  {
    "word": "勒克瑙",
    "pinyin": "Lèkènǎo",
    "part_of_speech": "noun",
    "meaning": "Lucknow",
    "chapter": 17,
    "source": "hsk1",
    "category": "city"
  },
  {
    "word": "浦那",
    "pinyin": "Pǔnà",
    "part_of_speech": "noun",
    "meaning": "Pune",
    "chapter": 17,
    "source": "hsk1",
    "category": "city"
  },
  {
    "word": "东京",
    "pinyin": "Dōngjīng",
    "part_of_speech": "noun",
    "meaning": "Tokyo (eastern capital)",
    "chapter": 17,
    "source": "hsk1",
    "category": "city"
  },
  {
    "word": "伦敦",
    "pinyin": "Lúndūn",
    "part_of_speech": "noun",
    "meaning": "London",
    "chapter": 17,
    "source": "hsk1",
    "category": "city"
  },
  {
    "word": "巴黎",
    "pinyin": "Bālí",
    "part_of_speech": "noun",
    "meaning": "Paris",
    "chapter": 17,
    "source": "hsk1",
    "category": "city"
  },
  {
    "word": "旧金山",
    "pinyin": "Jiùjīnshān",
    "part_of_speech": "noun",
    "meaning": "San Francisco (old gold mountain)",
    "chapter": 17,
    "source": "hsk1",
    "category": "city"
  },
  {
    "word": "南京",
    "pinyin": "Nánjīng",
    "part_of_speech": "noun",
    "meaning": "Nanjing (southern capital)",
    "chapter": 17,
    "source": "hsk1",
    "category": "city"
  }
]